LICENSE
README.md
setup.py
jhammer/__init__.py
jhammer/checkpoint.py
jhammer/config.py
jhammer/cumulative_metric.py
jhammer/distance_maps.py
jhammer/io.py
jhammer/log.py
jhammer/lr_schedulers.py
jhammer/lr_utils.py
jhammer/medical_image_converters.py
jhammer/metrics.py
jhammer/reductions.py
jhammer/statistics.py
jhammer/type_converters.py
jhammer.egg-info/PKG-INFO
jhammer.egg-info/SOURCES.txt
jhammer.egg-info/dependency_links.txt
jhammer.egg-info/requires.txt
jhammer.egg-info/top_level.txt
jhammer/image/__init__.py
jhammer/image/colors.py
jhammer/image/contrast.py
jhammer/image/overlay.py
jhammer/losses/__init__.py
jhammer/losses/dice_loss.py
jhammer/models/__init__.py
jhammer/models/unet.py
jhammer/models/unet_plus_plus.py
jhammer/samplers/__init__.py
jhammer/samplers/coordinate_generator.py
jhammer/samplers/grid_sampler.py
jhammer/samplers/patch_picker.py
jhammer/samplers/preloaded_data_loader.py
jhammer/samplers/preloaded_dataset.py
jhammer/samplers/utils.py
jhammer/transforms/__init__.py
jhammer/transforms/data_transforms.py
jhammer/transforms/distance_transforms.py
jhammer/transforms/image_transforms.py
jhammer/transforms/transforms.py