Metadata-Version: 2.1
Name: jhammer
Version: 3.0.8
Summary: My hammer for medical image processing and deap learning.
Author: Dai Jian
Author-email: daijian@stumail.ysu.edu.cn
Classifier: Programming Language :: Python :: 3.11
Classifier: License :: OSI Approved :: GNU General Public License v3 (GPLv3)
Classifier: Operating System :: OS Independent
Requires-Python: ~=3.11
License-File: LICENSE
Requires-Dist: numpy>=1.21.0
Requires-Dist: nibabel>=4.0.1
Requires-Dist: scipy>=1.7.3
Requires-Dist: medpy>=0.4.0
Requires-Dist: SimpleITK>=2.1.1.2
Requires-Dist: pydicom>=2.4.3
Requires-Dist: dicom2nifti>=2.4.8
Requires-Dist: lazyConfig
